rgs/.DS_Store
rgs/__init__.py
rgs/mndrpy/Combinatorics.py
rgs/mndrpy/DyckPaths.py
rgs/mndrpy/Matrix.csv
rgs/mndrpy/Meander.py
rgs/mndrpy/Pairing.py
rgs/mndrpy/Utility.py
rgs/mndrpy/__init__.py
rgs/pmaps/Graph.py
rgs/pmaps/OrderedTree.py
rgs/pmaps/PlanarGraph.py
rgs/pmaps/TreeUtility.py
rgs/pmaps/Triangulation.py
rgs/pmaps/__init__.py
rgs/ribbons/Ribbon.py
rgs/ribbons/Tiling.py
rgs/ribbons/Utility.py
rgs/ribbons/__init__.py
rgs-0.1.11.dist-info/LICENSE
rgs-0.1.11.dist-info/WHEEL
rgs-0.1.11.dist-info/METADATA
rgs-0.1.11.dist-info/RECORD
