Metadata-Version: 2.1
Name: rgs
Version: 0.1.11
Summary: A small package to display and manipulate random geometry structures like pairings, meanders, triangulations and tilings.
Home-page: https://github.com/slavakargin/RandomGeeometricStructures
License: MIT
Author: Vladislav Kargin
Author-email: slavakargin@yahoo.com
Requires-Python: >=3.7,<4.0
Classifier: License :: OSI Approved :: MIT License
Classifier: Programming Language :: Python :: 3
Classifier: Programming Language :: Python :: 3.7
Classifier: Programming Language :: Python :: 3.8
Classifier: Programming Language :: Python :: 3.9
Requires-Dist: itu.algs4
Requires-Dist: numdifftools
Requires-Dist: numpy
Project-URL: Repository, https://github.com/slavakargin/RandomGeeometricStructures
